{
  "objectives": [
    {
      "id": "95b383f3-aca3-43dd-b8e3-dc305d462abf",
      "name": "Ciclo 4",
      "description": "",
      "category": {
        "id": 0,
        "name": "Objetivo da empresa"
      },
      "owner": {
        "id": 1,
        "name": "Maurício Ribeiro Andrade",
        "photo": "https://randomuser.me/api/portraits/men/89.jpg"
      },
      "supporters": [],
      "visibility": "public",
      "cycle": {
        "id": "2023Q4",
        "name": "4° Trimestre 2023"
      },
      "createdAt": "2023-08-07T15:12:44.810Z",
      "startDate": "2023-10-01",
      "deadline": "2023-12-31",
      "finished": 0,
      "associate": null
    },
    {
      "id": "053e3d54-3536-4196-bc2e-3e928718881d",
      "name": "Objetivo 1",
      "description": "Descrição supimpa que pode ser longa para estar a quebra de texto nos detalhes do objetivo.",
      "category": {
        "id": 1,
        "name": "Objetivo do grupo"
      },
      "owner": {
        "id": 2,
        "name": "Fernanda Mendonça",
        "photo": "https://randomuser.me/api/portraits/women/62.jpg"
      },
      "supporters": [
        0,
        1
      ],
      "visibility": "public",
      "cycle": {
        "id": "2023Q3",
        "name": "3° Trimestre 2023"
      },
      "createdAt": "2023-08-08T12:59:21.191Z",
      "startDate": "2023-07-01",
      "deadline": "2023-09-30",
      "finished": 0,
      "conclusionPercent": 90
    },
    {
      "id": "de617d3a-f94c-4eb1-b905-146239b222ce",
      "name": "Objetivo 1 - 1",
      "description": "foi",
      "category": {
        "id": 1,
        "name": "Objetivo do grupo"
      },
      "owner": {
        "id": 0,
        "name": "Luiz Albuquerque",
        "photo": null
      },
      "supporters": [],
      "visibility": "public",
      "cycle": {
        "id": "2023Q3",
        "name": "3° Trimestre 2023"
      },
      "createdAt": "2023-08-15T14:59:54.536Z",
      "startDate": "2023-07-01",
      "deadline": "2023-09-30",
      "finished": 0,
      "associate": "053e3d54-3536-4196-bc2e-3e928718881d",
      "conclusionPercent": 22.6
    },
    {
      "id": "bc6f1b65-7949-4cd7-b7fc-a9becaf58dfc",
      "name": "Objetivo 1 - 1 - 1",
      "description": "Aqui também tem uma descrição grande para testar a descrição grande nos detalhes do objetivo.",
      "category": {
        "id": 2,
        "name": "Objetivo individual"
      },
      "owner": {
        "id": 1,
        "name": "Maurício Ribeiro Andrade",
        "photo": "https://randomuser.me/api/portraits/men/89.jpg"
      },
      "supporters": [
        2,
        0
      ],
      "visibility": "public",
      "cycle": {
        "id": "2023Q3",
        "name": "3° Trimestre 2023"
      },
      "createdAt": "2023-08-15T15:16:40.638Z",
      "startDate": "2023-07-01",
      "deadline": "2023-09-30",
      "finished": 0,
      "associate": "de617d3a-f94c-4eb1-b905-146239b222ce",
      "conclusionPercent": 50
    }
  ],
  "krs": [
    {
      "id": "8ebe6bf7-d423-497e-aeaa-774db22978b3",
      "name": "Kr teste",
      "description": "descrição",
      "owner": {
        "id": 1,
        "name": "Maurício Ribeiro Andrade",
        "photo": "https://randomuser.me/api/portraits/men/89.jpg"
      },
      "type": "percent",
      "objective": "bc6f1b65-7949-4cd7-b7fc-a9becaf58dfc",
      "progress": 0,
      "tasks": [
        {
          "id": "819981c6-de7a-42cd-8b96-604e8a51c3ee",
          "name": "",
          "checked": false
        }
      ]
    },
    {
      "id": "0cb90c1c-3d63-475d-a32c-2b75df41f30c",
      "name": "teste 2",
      "description": "",
      "owner": {
        "id": 0,
        "name": "Luiz Albuquerque",
        "photo": null
      },
      "type": "task",
      "objective": "bc6f1b65-7949-4cd7-b7fc-a9becaf58dfc",
      "progress": 0,
      "tasks": [
        {
          "id": "36157f2d-0d7f-49cf-ac59-5c07036b2285",
          "name": "Tarefa 1",
          "checked": false
        },
        {
          "id": "8221421f-cb60-4a87-92b8-1e4562b577ad",
          "name": "Tarefs 2",
          "checked": false
        }
      ]
    },
    {
      "id": "b556d12b-e601-4ad0-8f39-4a3f57ad215f",
      "name": "teste 3",
      "description": "asdfsdfdasfadsfadsfadsf",
      "owner": {
        "id": 1,
        "name": "Maurício Ribeiro Andrade",
        "photo": "https://randomuser.me/api/portraits/men/89.jpg"
      },
      "type": "value",
      "objective": "bc6f1b65-7949-4cd7-b7fc-a9becaf58dfc",
      "progress": 0,
      "tasks": [
        {
          "id": "dda34460-c0a1-4bd3-847b-160e32b91d04",
          "name": "",
          "checked": false
        }
      ],
      "value": 100000,
      "unit": "R$"
    }
  ],
  "cycles": [
    {
      "id": "2023Q3",
      "name": "3° Trimestre 2023"
    },
    {
      "id": "2023Q4",
      "name": "4° Trimestre 2023"
    }
  ],
  "users": [
    {
      "id": 0,
      "name": "Luiz Albuquerque",
      "photo": null
    },
    {
      "id": 1,
      "name": "Maurício Ribeiro Andrade",
      "photo": "https://randomuser.me/api/portraits/men/89.jpg"
    },
    {
      "id": 2,
      "name": "Fernanda Mendonça",
      "photo": "https://randomuser.me/api/portraits/women/62.jpg"
    }
  ]
}